npu_bench/mac.v
module mac(clk, rst, in_a, in_b, out_a, out_b, out_c);

parameter data_size = 32;

input rst;
input clk;
input [data_size-1:0] in_a;
input [data_size-1:0] in_b;
output [data_size-1:0] out_c;
output reg [data_size-1:0] out_a;
output reg [data_size-1:0] out_b;

reg [2*data_size-1:0] out_c_r;

always @(posedge clk or posedge rst)begin
  if(rst) begin
    out_a = 0;
    out_b = 0;
    out_c_r = 0;
  end
  else begin
    out_a = in_a;
    out_b = in_b;
    out_c_r = out_c + in_a * in_b;
  end
end

assign out_c = out_c_r[31:0];
 
endmodule

npu_bench/systolic_array.v
module systolic_array(clk, rst, a1, a2, a3, b1, b2, b3, c1, c2, c3, c4, c5, c6, c7, c8, c9);

parameter data_size = 32;

input clk;
input rst;
input [data_size-1:0] a1;
input [data_size-1:0] a2;
input [data_size-1:0] a3;
input [data_size-1:0] b1;
input [data_size-1:0] b2;
input [data_size-1:0] b3;

output [data_size-1:0] c1;
output [data_size-1:0] c2;
output [data_size-1:0] c3;
output [data_size-1:0] c4;
output [data_size-1:0] c5;
output [data_size-1:0] c6;
output [data_size-1:0] c7;
output [data_size-1:0] c8;
output [data_size-1:0] c9;

wire [data_size-1:0] a12;
wire [data_size-1:0] a23;
wire [data_size-1:0] a45;
wire [data_size-1:0] a56;
wire [data_size-1:0] a78;
wire [data_size-1:0] a89;

wire [data_size-1:0] b14;
wire [data_size-1:0] b25;
wire [data_size-1:0] b36;
wire [data_size-1:0] b47;
wire [data_size-1:0] b58;
wire [data_size-1:0] b69;

mac dut_mac1 (.clk(clk), .rst(rst), .in_a(a1), .in_b(b1), .out_a(a12), .out_b(b14), .out_c(c1));
mac dut_mac2 (.clk(clk), .rst(rst), .in_a(a12), .in_b(b2), .out_a(a23), .out_b(b25), .out_c(c2));
mac dut_mac3 (.clk(clk), .rst(rst), .in_a(a23), .in_b(b3), .out_a(), .out_b(b36), .out_c(c3));
mac dut_mac4 (.clk(clk), .rst(rst), .in_a(a2), .in_b(b14), .out_a(a45), .out_b(b47), .out_c(c4));
mac dut_mac5 (.clk(clk), .rst(rst), .in_a(a45), .in_b(b25), .out_a(a56), .out_b(b58), .out_c(c5));
mac dut_mac6 (.clk(clk), .rst(rst), .in_a(a56), .in_b(b36), .out_a(), .out_b(b69), .out_c(c6));
mac dut_mac7 (.clk(clk), .rst(rst), .in_a(a3), .in_b(b47), .out_a(a78), .out_b(), .out_c(c7));
mac dut_mac8 (.clk(clk), .rst(rst), .in_a(a78), .in_b(b58), .out_a(a89), .out_b(), .out_c(c8));
mac dut_mac9 (.clk(clk), .rst(rst), .in_a(a89), .in_b(b69), .out_a(), .out_b(), .out_c(c9));

endmodule

npu_bench/tb_systolic_array.v
`timescale 1ns / 100ps
module tb_systolic_array();

parameter data_size = 32;

reg clk;
reg rst;
reg [data_size-1:0] a1;
reg [data_size-1:0] a2;
reg [data_size-1:0] a3;
reg [data_size-1:0] b1;
reg [data_size-1:0] b2;
reg [data_size-1:0] b3;

wire [data_size-1:0] c1;
wire [data_size-1:0] c2;
wire [data_size-1:0] c3;
wire [data_size-1:0] c4;
wire [data_size-1:0] c5;
wire [data_size-1:0] c6;
wire [data_size-1:0] c7;
wire [data_size-1:0] c8;
wire [data_size-1:0] c9;

systolic_array dut1(
    .clk(clk), 
    .rst(rst), 
    .a1(a1), 
    .a2(a2), 
    .a3(a3), 
    .b1(b1), 
    .b2(b2), 
    .b3(b3), 
    .c1(c1), 
    .c2(c2), 
    .c3(c3), 
    .c4(c4), 
    .c5(c5), 
    .c6(c6), 
    .c7(c7), 
    .c8(c8), 
    .c9(c9));

initial begin
    $dumpfile("test.vcd");
    $dumpvars(0, tb_systolic_array);
    clk = 32'd1;
    rst = 32'd1;
    a1 = 32'd0; // all input values are 0 at initial.
    a2 = 32'd0;
    a3 = 32'd0;
    b1 = 32'd0;
    b2 = 32'd0;
    b3 = 32'd0;
    #5;  rst = 0;
    #5;  a1 = 32'd1; a2 = 32'd0; a3 = 32'd0; b1 = 32'd1; b2 = 32'd0; b3 = 32'd0;
    #10; a1 = 32'd2; a2 = 32'd4; a3 = 32'd0; b1 = 32'd4; b2 = 32'd2; b3 = 32'd0;
    #10; a1 = 32'd3; a2 = 32'd5; a3 = 32'd7; b1 = 32'd7; b2 = 32'd5; b3 = 32'd3;
    #10; a1 = 32'd0; a2 = 32'd6; a3 = 32'd8; b1 = 32'd0; b2 = 32'd8; b3 = 32'd6;
    #10; a1 = 32'd0; a2 = 32'd0; a3 = 32'd9; b1 = 32'd0; b2 = 32'd0; b3 = 32'd9;
    #10; a1 = 32'd0; a2 = 32'd0; a3 = 32'd0; b1 = 32'd0; b2 = 32'd0; b3 = 32'd0;
    #50;
    $finish;
end

    always #5 clk = ~clk;
    
endmodule

npu_bench/test.vcd
$date
	Fri May 12 23:29:09 2023
$end
$version
	Icarus Verilog
$end
$timescale
	100ps
$end
$scope module tb_systolic_array $end
$var wire 32 ! c9 [31:0] $end
$var wire 32 " c8 [31:0] $end
$var wire 32 # c7 [31:0] $end
$var wire 32 $ c6 [31:0] $end
$var wire 32 % c5 [31:0] $end
$var wire 32 & c4 [31:0] $end
$var wire 32 ' c3 [31:0] $end
$var wire 32 ( c2 [31:0] $end
$var wire 32 ) c1 [31:0] $end
$var reg 32 * a1 [31:0] $end
$var reg 32 + a2 [31:0] $end
$var reg 32 , a3 [31:0] $end
$var reg 32 - b1 [31:0] $end
$var reg 32 . b2 [31:0] $end
$var reg 32 / b3 [31:0] $end
$var reg 1 0 clk $end
$var reg 1 1 rst $end
$scope module dut1 $end
$var wire 32 2 a1 [31:0] $end
$var wire 32 3 a2 [31:0] $end
$var wire 32 4 a3 [31:0] $end
$var wire 32 5 b1 [31:0] $end
$var wire 32 6 b2 [31:0] $end
$var wire 32 7 b3 [31:0] $end
$var wire 1 0 clk $end
$var wire 1 1 rst $end
$var wire 32 8 c9 [31:0] $end
$var wire 32 9 c8 [31:0] $end
$var wire 32 : c7 [31:0] $end
$var wire 32 ; c6 [31:0] $end
$var wire 32 < c5 [31:0] $end
$var wire 32 = c4 [31:0] $end
$var wire 32 > c3 [31:0] $end
$var wire 32 ? c2 [31:0] $end
$var wire 32 @ c1 [31:0] $end
$var wire 32 A b69 [31:0] $end
$var wire 32 B b58 [31:0] $end
$var wire 32 C b47 [31:0] $end
$var wire 32 D b36 [31:0] $end
$var wire 32 E b25 [31:0] $end
$var wire 32 F b14 [31:0] $end
$var wire 32 G a89 [31:0] $end
$var wire 32 H a78 [31:0] $end
$var wire 32 I a56 [31:0] $end
$var wire 32 J a45 [31:0] $end
$var wire 32 K a23 [31:0] $end
$var wire 32 L a12 [31:0] $end
$scope module dut_mac1 $end
$var wire 1 0 clk $end
$var wire 32 M in_a [31:0] $end
$var wire 32 N in_b [31:0] $end
$var wire 1 1 rst $end
$var wire 32 O out_c [31:0] $end
$var reg 32 P out_a [31:0] $end
$var reg 32 Q out_b [31:0] $end
$var reg 64 R out_c_r [63:0] $end
$upscope $end
$scope module dut_mac2 $end
$var wire 1 0 clk $end
$var wire 32 S in_a [31:0] $end
$var wire 32 T in_b [31:0] $end
$var wire 1 1 rst $end
$var wire 32 U out_c [31:0] $end
$var reg 32 V out_a [31:0] $end
$var reg 32 W out_b [31:0] $end
$var reg 64 X out_c_r [63:0] $end
$upscope $end
$scope module dut_mac3 $end
$var wire 1 0 clk $end
$var wire 32 Y in_a [31:0] $end
$var wire 32 Z in_b [31:0] $end
$var wire 1 1 rst $end
$var wire 32 [ out_c [31:0] $end
$var reg 32 \ out_a [31:0] $end
$var reg 32 ] out_b [31:0] $end
$var reg 64 ^ out_c_r [63:0] $end
$upscope $end
$scope module dut_mac4 $end
$var wire 1 0 clk $end
$var wire 32 _ in_a [31:0] $end
$var wire 32 ` in_b [31:0] $end
$var wire 1 1 rst $end
$var wire 32 a out_c [31:0] $end
$var reg 32 b out_a [31:0] $end
$var reg 32 c out_b [31:0] $end
$var reg 64 d out_c_r [63:0] $end
$upscope $end
$scope module dut_mac5 $end
$var wire 1 0 clk $end
$var wire 32 e in_a [31:0] $end
$var wire 32 f in_b [31:0] $end
$var wire 1 1 rst $end
$var wire 32 g out_c [31:0] $end
$var reg 32 h out_a [31:0] $end
$var reg 32 i out_b [31:0] $end
$var reg 64 j out_c_r [63:0] $end
$upscope $end
$scope module dut_mac6 $end
$var wire 1 0 clk $end
$var wire 32 k in_a [31:0] $end
$var wire 32 l in_b [31:0] $end
$var wire 1 1 rst $end
$var wire 32 m out_c [31:0] $end
$var reg 32 n out_a [31:0] $end
$var reg 32 o out_b [31:0] $end
$var reg 64 p out_c_r [63:0] $end
$upscope $end
$scope module dut_mac7 $end
$var wire 1 0 clk $end
$var wire 32 q in_a [31:0] $end
$var wire 32 r in_b [31:0] $end
$var wire 1 1 rst $end
$var wire 32 s out_c [31:0] $end
$var reg 32 t out_a [31:0] $end
$var reg 32 u out_b [31:0] $end
$var reg 64 v out_c_r [63:0] $end
$upscope $end
$scope module dut_mac8 $end
$var wire 1 0 clk $end
$var wire 32 w in_a [31:0] $end
$var wire 32 x in_b [31:0] $end
$var wire 1 1 rst $end
$var wire 32 y out_c [31:0] $end
$var reg 32 z out_a [31:0] $end
$var reg 32 { out_b [31:0] $end
$var reg 64 | out_c_r [63:0] $end
$upscope $end
$scope module dut_mac9 $end
$var wire 1 0 clk $end
$var wire 32 } in_a [31:0] $end
$var wire 32 ~ in_b [31:0] $end
$var wire 1 1 rst $end
$var wire 32 !" out_c [31:0] $end
$var reg 32 "" out_a [31:0] $end
$var reg 32 #" out_b [31:0] $end
$var reg 64 $" out_c_r [63:0] $end
$upscope $end
$upscope $end
$upscope $end
$enddefinitions $end
#0
$dumpvars
b0 $"
b0 #"
b0 ""
b0 !"
b0 ~
b0 }
b0 |
b0 {
b0 z
b0 y
b0 x
b0 w
b0 v
b0 u
b0 t
b0 s
b0 r
b0 q
b0 p
b0 o
b0 n
b0 m
b0 l
b0 k
b0 j
b0 i
b0 h
b0 g
b0 f
b0 e
b0 d
b0 c
b0 b
b0 a
b0 `
b0 _
b0 ^
b0 ]
b0 \
b0 [
b0 Z
b0 Y
b0 X
b0 W
b0 V
b0 U
b0 T
b0 S
b0 R
b0 Q
b0 P
b0 O
b0 N
b0 M
b0 L
b0 K
b0 J
b0 I
b0 H
b0 G
b0 F
b0 E
b0 D
b0 C
b0 B
b0 A
b0 @
b0 ?
b0 >
b0 =
b0 <
b0 ;
b0 :
b0 9
b0 8
b0 7
b0 6
b0 5
b0 4
b0 3
b0 2
11
10
b0 /
b0 .
b0 -
b0 ,
b0 +
b0 *
b0 )
b0 (
b0 '
b0 &
b0 %
b0 $
b0 #
b0 "
b0 !
$end
#50
00
01
#100
b1 )
b1 @
b1 O
b1 R
b1 F
b1 Q
b1 `
b1 L
b1 P
b1 S
10
b1 -
b1 5
b1 N
b1 *
b1 2
b1 M
#150
00
#200
b1001 )
b1001 @
b1001 O
b10 (
b10 ?
b10 U
b100 &
b100 =
b100 a
b1001 R
b100 F
b100 Q
b100 `
b10 L
b10 P
b10 S
b10 X
b10 E
b10 W
b10 f
b1 K
b1 V
b1 Y
b100 d
b1 C
b1 c
b1 r
b100 J
b100 b
b100 e
10
b10 .
b10 6
b10 T
b100 -
b100 5
b100 N
b100 +
b100 3
b100 _
b10 *
b10 2
b10 M
#250
00
#300
b111 #
b111 :
b111 s
b1000 %
b1000 <
b1000 g
b11000 &
b11000 =
b11000 a
b11 '
b11 >
b11 [
b1100 (
b1100 ?
b1100 U
b11110 )
b11110 @
b11110 O
b111 v
b1 u
b111 H
b111 t
b111 w
b1000 j
b10 B
b10 i
b10 x
b100 I
b100 h
b100 k
b11000 d
b100 C
b100 c
b100 r
b101 J
b101 b
b101 e
b11 ^
b11 D
b11 ]
b11 l
b1 \
b1100 X
b101 E
b101 W
b101 f
b10 K
b10 V
b10 Y
b11110 R
b111 F
b111 Q
b111 `
b11 L
b11 P
b11 S
10
b11 /
b11 7
b11 Z
b101 .
b101 6
b101 T
b111 -
b111 5
b111 N
b111 ,
b111 4
b111 q
b101 +
b101 3
b101 _
b11 *
b11 2
b11 M
#350
00
#400
b100100 (
b100100 ?
b100100 U
b1111 '
b1111 >
b1111 [
b1000010 &
b1000010 =
b1000010 a
b100001 %
b100001 <
b100001 g
b1100 $
b1100 ;
b1100 m
b100111 #
b100111 :
b100111 s
b1110 "
b1110 9
b1110 y
b0 F
b0 Q
b0 `
b0 L
b0 P
b0 S
b100100 X
b1000 E
b1000 W
b1000 f
b11 K
b11 V
b11 Y
b1111 ^
b110 D
b110 ]
b110 l
b10 \
b1000010 d
b111 C
b111 c
b111 r
b110 J
b110 b
b110 e
b100001 j
b101 B
b101 i
b101 x
b101 I
b101 h
b101 k
b1100 p
b11 A
b11 o
b11 ~
b100 n
b100111 v
b100 u
b1000 H
b1000 t
b1000 w
b1110 |
b10 {
b111 G
b111 z
b111 }
10
b110 /
b110 7
b110 Z
b1000 .
b1000 6
b1000 T
b0 -
b0 5
b0 N
b1000 ,
b1000 4
b1000 q
b110 +
b110 3
b110 _
b0 *
b0 2
b0 M
#450
00
#500
b10101 !
b10101 8
b10101 !"
b110110 "
b110110 9
b110110 y
b1100110 #
b1100110 :
b1100110 s
b101010 $
b101010 ;
b101010 m
b1010001 %
b1010001 <
b1010001 g
b101010 '
b101010 >
b101010 [
b10101 $"
b11 #"
b111 ""
b110110 |
b101 {
b1000 G
b1000 z
b1000 }
b1100110 v
b111 u
b1001 H
b1001 t
b1001 w
b101010 p
b110 A
b110 o
b110 ~
b101 n
b1010001 j
b1000 B
b1000 i
b1000 x
b110 I
b110 h
b110 k
b0 C
b0 c
b0 r
b0 J
b0 b
b0 e
b101010 ^
b1001 D
b1001 ]
b1001 l
b11 \
b0 E
b0 W
b0 f
b0 K
b0 V
b0 Y
10
b1001 /
b1001 7
b1001 Z
b0 .
b0 6
b0 T
b1001 ,
b1001 4
b1001 q
b0 +
b0 3
b0 _
#550
00
#600
b1100000 $
b1100000 ;
b1100000 m
b1111110 "
b1111110 9
b1111110 y
b1000101 !
b1000101 8
b1000101 !"
b0 D
b0 ]
b0 l
b0 \
b0 B
b0 i
b0 x
b0 I
b0 h
b0 k
b1100000 p
b1001 A
b1001 o
b1001 ~
b110 n
b0 u
b0 H
b0 t
b0 w
b1111110 |
b1000 {
b1001 G
b1001 z
b1001 }
b1000101 $"
b110 #"
b1000 ""
10
b0 /
b0 7
b0 Z
b0 ,
b0 4
b0 q
#650
00
#700
b10010110 !
b10010110 8
b10010110 !"
b10010110 $"
b1001 #"
b1001 ""
b0 {
b0 G
b0 z
b0 }
b0 A
b0 o
b0 ~
b0 n
10
#750
00
#800
b0 #"
b0 ""
10
